LICENSE
MANIFEST.in
README.md
requirements.txt
setup.py
aws_billing/__init__.py
aws_billing/admin.py
aws_billing/aws_billing.py
aws_billing/models.py
aws_billing/tests.py
aws_billing/views.py
aws_billing/management/__init__.py
aws_billing/management/commands/__init__.py
aws_billing/management/commands/aws_costs.py
aws_billing/management/commands/process_aws_billing.py
django_aws_billing.egg-info/PKG-INFO
django_aws_billing.egg-info/SOURCES.txt
django_aws_billing.egg-info/dependency_links.txt
django_aws_billing.egg-info/requires.txt
django_aws_billing.egg-info/top_level.txt